MANIFEST.in
README.rst
setup.cfg
setup.py
pyramid_breve/__init__.py
pyramid_breve/monitor.py
pyramid_breve/renderer.py
pyramid_breve.egg-info/PKG-INFO
pyramid_breve.egg-info/SOURCES.txt
pyramid_breve.egg-info/dependency_links.txt
pyramid_breve.egg-info/requires.txt
pyramid_breve.egg-info/top_level.txt