Metadata-Version: 1.0
Name: pyramid-breve
Version: 0.7.0
Summary: Breve template engine renderer for Pyramid Web Framework
Home-page: http://github.com/momyc/pyramid-breve
Author: Alexander Kulakov
Author-email: a.kulakov@mail.ru
License: MIT
Keywords: pyramid breve
Platform: UNKNOWN
